Workbook
Name Aporte: APP!$D$17
Name dividendo_mensais: APP!$D$21
Name patrimonio_acumulado: APP!$D$20
Name Qtd_anos: APP!$D$18
Name rendimento_carteira: APP!$D$13
Name salario: APP!$D$12
Name sugestao_investimento: APP!$D$14
Name Taxa_mensal: APP!$D$19

Sheet APP
B11: Conigurações
B12: Salário | D12: 2092
B13: Rendimento Cartéira | D13: 0.0098
B14: Sugestão de Investimento (30%) | D14: =D12*30% -> 627.6
B16: INVESTIMENTO MENSAL
B17: Quanto investir por mês | D17: 627
B18: Por quantos anos? | D18: 5
B19: Taxa de rendimento mensal? | D19: 0.01079
B20: Patrimonio acumulado? | D20: =FV(D19,D18*12,D17*-1) -> 52528.125
B21: Dividendos mensais? | D21: =D20*$D$13 -> 514.77563
B23: Cenários | D23: Dividendo
A24: 2 | B24: Quanto em 2 Anos? | C24: =FV($D$19,$A24*12,$D$17*-1) -> 17071.722 | D24: =C24*rendimento_carteira -> 167.30288
A25: 5 | B25: Quanto em 5 Anos? | C25: =FV($D$19,$A25*12,$D$17*-1) -> 52528.125 | D25: =C25*rendimento_carteira -> 514.77563
A26: 10 | B26: Quanto em 10 Anos? | C26: =FV($D$19,$A26*12,$D$17*-1) -> 152539.2 | D26: =C26*rendimento_carteira -> 1494.8842
A27: 20 | B27: Quanto em 20 Anos? | C27: =FV($D$19,$A27*12,$D$17*-1) -> 705499.4 | D27: =C27*rendimento_carteira -> 6913.8941
A28: 30 | B28: Quanto em 30 Anos? | C28: =FV($D$19,$A28*12,$D$17*-1) -> 2710000.4 | D28: =C28*rendimento_carteira -> 26558.004
B31: PERFIL | C31: MODERADO
B32: Valor a ser investido por mês | C32: =Aporte -> 627
B34: Tipo de FII | C34: Percentual Sugerido | D34: Valores
B35: Papel | C35: =VLOOKUP($C$31&"-"&B35,Planilha2!$A:$D,4,) -> 0.32 | D35: =C35*$C$32 -> 200.64
B36: Tijolo | C36: =VLOOKUP($C$31&"-"&B36,Planilha2!$A:$D,4,) -> 0.35 | D36: =C36*$C$32 -> 219.45
B37: Hibridos | C37: =VLOOKUP($C$31&"-"&B37,Planilha2!$A:$D,4,) -> 0.08 | D37: =C37*$C$32 -> 50.16
B38: FOF | C38: =VLOOKUP($C$31&"-"&B38,Planilha2!$A:$D,4,) -> 0.05 | D38: =C38*$C$32 -> 31.35
B39: Desinvolvimento | C39: =VLOOKUP($C$31&"-"&B39,Planilha2!$A:$D,4,) -> 0.1 | D39: =C39*$C$32 -> 62.7
B40: Hotelarias | C40: =VLOOKUP($C$31&"-"&B40,Planilha2!$A:$D,4,) -> 0.1 | D40: =C40*$C$32 -> 62.7
D41: =SUM(D35:D40) -> 627

Sheet Planilha2
A2: Chave Composta | B2: Perfil | C2: TIPO DE FIIS | D2: %
A3: =B3&"-"&C3 -> CONSERVADOR-Papel | B3: CONSERVADOR | C3: Papel | D3: 0.3
A4: =B4&"-"&C4 -> CONSERVADOR-Tijolo | B4: CONSERVADOR | C4: Tijolo | D4: 0.5 | H4: %
A5: =B5&"-"&C5 -> CONSERVADOR-Hibridos | B5: CONSERVADOR | C5: Hibridos | D5: 0.1 | G5: MODERADO-Tijolo | H5: =VLOOKUP(G5,$A:$D,4,) -> 0.35
A6: =B6&"-"&C6 -> CONSERVADOR-FOF | B6: CONSERVADOR | C6: FOF | D6: 0.1
A7: =B7&"-"&C7 -> CONSERVADOR-Desinvolvimento | B7: CONSERVADOR | C7: Desinvolvimento | D7: 0
A8: =B8&"-"&C8 -> CONSERVADOR-Hotelarias | B8: CONSERVADOR | C8: Hotelarias | D8: 0
A9: =B9&"-"&C9 -> MODERADO-Papel | B9: MODERADO | C9: Papel | D9: 0.32
A10: =B10&"-"&C10 -> MODERADO-Tijolo | B10: MODERADO | C10: Tijolo | D10: 0.35
A11: =B11&"-"&C11 -> MODERADO-Hibridos | B11: MODERADO | C11: Hibridos | D11: 0.08
A12: =B12&"-"&C12 -> MODERADO-FOF | B12: MODERADO | C12: FOF | D12: 0.05
A13: =B13&"-"&C13 -> MODERADO-Desinvolvimento | B13: MODERADO | C13: Desinvolvimento | D13: 0.1
A14: =B14&"-"&C14 -> MODERADO-Hotelarias | B14: MODERADO | C14: Hotelarias | D14: 0.1
A15: =B15&"-"&C15 -> AGRESSIVO-Papel | B15: AGRESSIVO | C15: Papel | D15: 0.5
A16: =B16&"-"&C16 -> AGRESSIVO-Tijolo | B16: AGRESSIVO | C16: Tijolo | D16: 0.1
A17: =B17&"-"&C17 -> AGRESSIVO-Hibridos | B17: AGRESSIVO | C17: Hibridos | D17: 0.05
... A20: =B20&"-"&C20 -> AGRESSIVO-Hotelarias | B20: AGRESSIVO | C20: Hotelarias | D20: 0.1
